piedb/__init__.py
piedb/db.py
piedb/error.py
piedb/util.py
piedb-0.1.1.dist-info/LICENSE
piedb-0.1.1.dist-info/METADATA
piedb-0.1.1.dist-info/WHEEL
piedb-0.1.1.dist-info/top_level.txt
piedb-0.1.1.dist-info/RECORD
