Metadata-Version: 2.1
Name: piedb
Version: 0.1.1
Summary: A lightweight JSON-based database
Home-page: https://github.com/shubham14243/piedb
Author: Shubham Kumar Gupta
Author-email: skgsmasher14243@gmail.com
License: MIT
Platform: UNKNOWN
Classifier: Programming Language :: Python :: 3
Classifier: License :: OSI Approved :: MIT License
Classifier: Operating System :: OS Independent
Requires-Python: >=3.6
License-File: LICENSE
